quangpy/__init__.py
quangpy/joint_scale.py
quangpy/utils.py
quangpy/var_decomp.py
quangpy/wls.py
quangpy-0.1.4.dist-info/METADATA
quangpy-0.1.4.dist-info/WHEEL
quangpy-0.1.4.dist-info/licenses/LICENSE
quangpy-0.1.4.dist-info/RECORD
