Metadata-Version: 2.4
Name: quangpy
Version: 0.1.4
Summary: Simple package for quantitative genetic analysis.
Author-email: r1cheu <chenrulei@cemps.ac.cn>
License: MIT License
License-File: LICENSE
Classifier: Development Status :: 4 - Beta
Classifier: Programming Language :: Python
Requires-Python: >=3.11
Requires-Dist: numpy
Requires-Dist: pandas
Requires-Dist: scipy
Requires-Dist: statsmodels
Provides-Extra: dev
Requires-Dist: pre-commit; extra == 'dev'
